mmap_ninja_dataframe/__init__.py
mmap_ninja_dataframe/base.py
mmap_ninja_dataframe/dense.py
mmap_ninja_dataframe/sparse.py
mmap_ninja_dataframe-0.5.0.dist-info/licenses/LICENSE
mmap_ninja_dataframe-0.5.0.dist-info/METADATA
mmap_ninja_dataframe-0.5.0.dist-info/WHEEL
mmap_ninja_dataframe-0.5.0.dist-info/top_level.txt
mmap_ninja_dataframe-0.5.0.dist-info/RECORD
