Metadata-Version: 2.4
Name: mmap_ninja_dataframe
Version: 0.5.0
Summary: mmap_ninja_dataframe: Memory mapped data structures
Author-email: Hristo Vrigazov <hvrigazov@gmail.com>
License: MIT
Classifier: License :: OSI Approved :: MIT License
Classifier: Programming Language :: Python :: 3
Classifier: Programming Language :: Python :: 3.4
Classifier: Programming Language :: Python :: 3.5
Classifier: Programming Language :: Python :: 3.6
Classifier: Programming Language :: Python :: 3.7
Classifier: Programming Language :: Python :: 3.8
Classifier: Programming Language :: Python :: 3.9
Classifier: Programming Language :: Python :: 3.10
Classifier: Programming Language :: Python :: 3.11
Classifier: Programming Language :: Python :: 3.12
Classifier: Operating System :: OS Independent
License-File: LICENSE
Requires-Dist: mmap_ninja
Requires-Dist: numpy
Dynamic: license-file
